library_contents/__init__.py
library_contents/priority.py
library_contents/summary.py
library_contents/verify.py
library_contents-0.1.dist-info/METADATA
library_contents-0.1.dist-info/WHEEL
library_contents-0.1.dist-info/top_level.txt
library_contents-0.1.dist-info/RECORD
