Metadata-Version: 2.1
Name: library_contents
Version: 0.1
Summary: A collection of independent libraries for diff functionalities
Author: Maitreyee_M
